treelike
