Metadata-Version: 1.1
Name: TreeLike
Version: 0.2.4
Summary: Helpers for creating and traversing recursively nested data structures in Python.
Home-page: http://github.com/iskandr/treelike
Author: Alex Rubinsteyn
Author-email: alexr@cs.nyu.edu
License: BSD
Platform: UNKNOWN
Classifier: Development Status :: 3 - Alpha
Classifier: Topic :: Software Development :: Libraries
Classifier: License :: OSI Approved :: BSD License
Classifier: Intended Audience :: Developers
Classifier: Programming Language :: Python :: 2.7
